verilog-learning/rtl/counter4.sv
module counter4 (
    input logic clk,
    input logic n_rst,
    input logic enable,
    output logic [3:0]count
); 

always_ff @( posedge clk or negedge n_rst ) begin
    if (!n_rst)
        count <= 4'd0;
    else if (enable)
        count <= count + 4'd1;
end

endmodule

verilog-learning/tb/tb_counter4.sv
`timescale 1ns/1ps

module tb_counter4;

    logic clk;
    logic n_rst;
    logic enable;
    logic [3:0]count;
    
    counter4 dut (
        .clk(clk),
        .n_rst(n_rst),
        .enable(enable),
        .count(count)
    );

    task automatic check_reset (); 

    begin
        n_rst = 1'b0; // reset enabled
        #1;

        if (count != 4'd0) begin
            $display("Failed reset task"); 
        end

        n_rst = 1'b1;
        #1;

    end

    endtask

    task automatic check_enable (
        input logic enable_test,
        input logic [3:0]count_expected
    );

        begin
            n_rst = 1; // disable reset
            enable = enable_test;

            @(posedge clk)
            #1;
            if (count != count_expected) begin
                $display("Failed capture test"); 
            end
        end

    endtask

    always #5 clk = ~clk;

    initial begin
        $dumpfile("build/counter4.vcd");
        $dumpvars(0, tb_counter4);

        clk    = 1'b0;
        n_rst  = 1'b1;
        enable = 1'b0;
        
        check_reset();
        check_enable(1'b0, 4'd0);
        check_enable(1'b1, 4'd1);
        check_enable(1'b1, 4'd2);
        check_enable(1'b0, 4'd2);

        for (int i = 3; i < 16; i++) begin
            check_enable(1'b1, i);
        end

        $display("4-bit counter test passed.");
        $finish;
    end

endmodule

verilog-learning/build/counter4.vcd
$date
	Sun May 31 06:10:37 2026
$end
$version
	Icarus Verilog
$end
$timescale
	1ps
$end
$scope module tb_counter4 $end
$var wire 4 ! count [3:0] $end
$var reg 1 " clk $end
$var reg 1 # enable $end
$var reg 1 $ n_rst $end
$scope module dut $end
$var wire 1 " clk $end
$var wire 1 # enable $end
$var wire 1 $ n_rst $end
$var reg 4 % count [3:0] $end
$upscope $end
$scope begin $ivl_for_loop0 $end
$var integer 32 & i [31:0] $end
$upscope $end
$scope task check_enable $end
$upscope $end
$scope task check_reset $end
$upscope $end
$upscope $end
$enddefinitions $end
$comment Show the parameter values. $end
$dumpall
$end
#0
$dumpvars
b0 &
b0 %
0$
0#
0"
b0 !
$end
#1000
1$
#5000
1"
#6000
1#
#10000
0"
#15000
b1 !
b1 %
1"
#20000
0"
#25000
b10 !
b10 %
1"
#26000
0#
#30000
0"
#35000
1"
#36000
1#
b11 &
#40000
0"
#45000
b11 !
b11 %
1"
#46000
b100 &
#50000
0"
#55000
b100 !
b100 %
1"
#56000
b101 &
#60000
0"
#65000
b101 !
b101 %
1"
#66000
b110 &
#70000
0"
#75000
b110 !
b110 %
1"
#76000
b111 &
#80000
0"
#85000
b111 !
b111 %
1"
#86000
b1000 &
#90000
0"
#95000
b1000 !
b1000 %
1"
#96000
b1001 &
#100000
0"
#105000
b1001 !
b1001 %
1"
#106000
b1010 &
#110000
0"
#115000
b1010 !
b1010 %
1"
#116000
b1011 &
#120000
0"
#125000
b1011 !
b1011 %
1"
#126000
b1100 &
#130000
0"
#135000
b1100 !
b1100 %
1"
#136000
b1101 &
#140000
0"
#145000
b1101 !
b1101 %
1"
#146000
b1110 &
#150000
0"
#155000
b1110 !
b1110 %
1"
#156000
b1111 &
#160000
0"
#165000
b1111 !
b1111 %
1"
#166000
b10000 &
