verilog-learning/rtl/d_ff.sv
module d_ff (
    input logic D,
    input logic clk,
    input logic n_rst, // reset when 0, normal operation on 1
    output logic Q,
    output logic Q_not
); 

    always_ff @(posedge clk or negedge n_rst) begin
        if (!n_rst) 
            Q <= 1'b0;
        else   
            Q <= D;
    end

    assign Q_not = ~Q; 

endmodule

verilog-learning/tb/tb_d_ff.sv
`timescale 1ns/1ps

module tb_d_ff;

    logic D;
    logic clk;
    logic n_rst; // reset when 0, normal operation on 1
    logic Q;
    logic Q_not;

    d_ff dut (
        .Q(Q),
        .Q_not(Q_not),
        .n_rst(n_rst),
        .D(D),
        .clk(clk)
    );

    task automatic check_reset (); 

    begin
        n_rst = 1'b0; // reset enabled
        #1;

        if (Q !== 1'b0 || Q_not !== 1'b1) begin
            $fatal(1, "Failed reset task"); 
        end

        n_rst = 1'b1;
        #1;

    end

    endtask

    task automatic check_capture (
        input logic D_test,
        input logic Q_expected,
        input logic Q_not_expected
    );

        begin
            n_rst = 1; // disable reset
            D = D_test;

            @(posedge clk)
            #1;
            if (Q !== Q_expected || Q_not !== Q_not_expected) begin
                $fatal(1, "Failed capture test"); 
            end
        end

    endtask

    always #5 clk = ~clk;

    initial begin
        $dumpfile("build/d_ff.vcd");
        $dumpvars(0, tb_d_ff);

        clk = 1'b0;
        D = 1'b0;
        n_rst = 1'b0; // reset when 0, normal operation on 1

        check_reset();
        check_capture(1'b0, 1'b0, 1'b1);
        check_capture(1'b1, 1'b1, 1'b0);
        check_capture(1'b0, 1'b0, 1'b1);
        check_capture(1'b1, 1'b1, 1'b0);
        
        $finish;
    end

endmodule

verilog-learning/build/d_ff.vcd
$date
	Sun May 31 06:16:31 2026
$end
$version
	Icarus Verilog
$end
$timescale
	1ps
$end
$scope module tb_d_ff $end
$var wire 1 ! Q_not $end
$var wire 1 " Q $end
$var reg 1 # D $end
$var reg 1 $ clk $end
$var reg 1 % n_rst $end
$scope module dut $end
$var wire 1 # D $end
$var wire 1 ! Q_not $end
$var wire 1 $ clk $end
$var wire 1 % n_rst $end
$var reg 1 " Q $end
$upscope $end
$scope task check_capture $end
$upscope $end
$scope task check_reset $end
$upscope $end
$upscope $end
$enddefinitions $end
$comment Show the parameter values. $end
$dumpall
$end
#0
$dumpvars
0%
0$
0#
0"
1!
$end
#1000
1%
#5000
1$
#6000
1#
#10000
0$
#15000
0!
1"
1$
#16000
0#
#20000
0$
#25000
1!
0"
1$
#26000
1#
#30000
0$
#35000
0!
1"
1$
