verilog-learning/rtl/full_adder.sv
module full_adder (
    input logic A0,
    input logic B0,
    input logic Cin,
    output logic Sum,
    output logic Cout
);

assign Sum = A0 ^ B0 ^ Cin;
assign Cout = (A0 & B0) | (Cin & B0) | (Cin & A0);

endmodule

verilog-learning/tb/tb_full_adder.sv
`timescale 1ns/1ps

module tb_full_adder;

    logic A0;
    logic B0;
    logic Cin;
    logic Cout;
    logic Sum;

    full_adder dut (
        .A0(A0),
        .B0(B0),
        .Cin(Cin),
        .Cout(Cout),
        .Sum(Sum)
    ); 

    task automatic check (
        input logic test_a;
        input logic test_b;
        input logic test_cin;
        output logic expected_cout;
        output logic expected_sum;
    ); 

        begin
           A0 = test_a;
           B0 = test_b;
           Cin = test_cin;
           
           #1;

           if (Sum !== expected_sum || Cout !== expected_cout) begin
                $fatal("Failed: A0=%0b B0=%0b Cin=%0b | expected Sum=%0b Cout=%0b, got Sum=%0b Cout=%0b", A0, B0, Cin, expected_sum, expected_cout, Sum, Cout); 
           end

           #9;
        end
    endtask 

    initial begin
        $dumpfile("build/full_adder.vcd");
        $dumpvars(0, tb_full_adder);

        Cin = 0; A0 = 0; B0 = 0; #10;
        Cin = 0; A0 = 0; B0 = 1; #10;
        Cin = 0; A0 = 1; B0 = 0; #10;
        Cin = 0; A0 = 1; B0 = 1; #10;

        Cin = 1; A0 = 0; B0 = 0; #10;
        Cin = 1; A0 = 0; B0 = 1; #10;
        Cin = 1; A0 = 1; B0 = 0; #10;
        Cin = 1; A0 = 1; B0 = 1; #10;

        $finish;
    end

endmodule

verilog-learning/build/full_adder.vcd
$date
	Fri May 29 07:42:05 2026
$end
$version
	Icarus Verilog
$end
$timescale
	1ps
$end
$scope module tb_full_adder $end
$var wire 1 ! Sum $end
$var wire 1 " Cout $end
$var reg 1 # A0 $end
$var reg 1 $ B0 $end
$var reg 1 % Cin $end
$scope module dut $end
$var wire 1 # A0 $end
$var wire 1 $ B0 $end
$var wire 1 % Cin $end
$var wire 1 " Cout $end
$var wire 1 ! Sum $end
$upscope $end
$upscope $end
$enddefinitions $end
$comment Show the parameter values. $end
$dumpall
$end
#0
$dumpvars
0%
0$
0#
0"
0!
$end
#10000
1!
1$
#20000
0$
1#
#30000
1"
0!
1$
#40000
0"
1!
0$
0#
1%
#50000
1"
0!
1$
#60000
0$
1#
#70000
1!
1$
