verilog-learning/rtl/shift_register4.sv
module shift_register4 (
    input logic n_rst,
    input logic enable,
    input logic clk,
    input logic shift_in,
    output logic shift_out,
    output logic [3:0]q
);

always_ff @( posedge clk or negedge n_rst ) begin
    if (!n_rst) begin
        q <= 4'b0;
        shift_out <= 4'b0;
    end else if (enable) begin
        shift_out <= q[0];
        q[0] <= q[1];
        q[1] <= q[2];
        q[2] <= q[3];
        q[3] <= shift_in;
    end
end

endmodule

verilog-learning/tb/tb_shift_register4.sv
`timescale 1ns/1ps

module tb_shift_register4;

    logic clk;
    logic n_rst;
    logic enable;
    logic shift_in;
    logic shift_out;
    logic [3:0] q;
    
    shift_register4 dut (
        .clk(clk),
        .n_rst(n_rst),
        .enable(enable),
        .shift_in(shift_in),
        .shift_out(shift_out),
        .q(q)
    );

    always #5 clk = ~clk;

    task automatic check_reset(); 
        begin
            n_rst   = 1'b0;
            enable  = 1'b0;
            shift_in = 1'b0;
            #1;

            if (q !== 4'b0000 || shift_out !== 1'b0) begin
                $fatal(1, "FAILED reset: expected q=0000 shift_out=0, got q=%04b shift_out=%0b",
                       q, shift_out); 
            end

            n_rst = 1'b1;
            #1;
        end
    endtask

    task automatic check_shift(
        input logic       test_shift_in,
        input logic [3:0] expected_q,
        input logic       expected_shift_out
    );
        begin
            n_rst    = 1'b1;
            enable   = 1'b1;
            shift_in = test_shift_in;

            @(posedge clk);
            #1;

            if (q !== expected_q || shift_out !== expected_shift_out) begin
                $fatal(1, "FAILED shift: shift_in=%0b expected q=%04b shift_out=%0b, got q=%04b shift_out=%0b",
                       shift_in, expected_q, expected_shift_out, q, shift_out);
            end
        end
    endtask

    task automatic check_hold(
        input logic       test_shift_in,
        input logic [3:0] expected_q,
        input logic       expected_shift_out
    );
        begin
            n_rst    = 1'b1;
            enable   = 1'b0;
            shift_in = test_shift_in;

            @(posedge clk);
            #1;

            if (q !== expected_q || shift_out !== expected_shift_out) begin
                $fatal(1, "FAILED hold: expected q=%04b shift_out=%0b, got q=%04b shift_out=%0b",
                       expected_q, expected_shift_out, q, shift_out);
            end
        end
    endtask

    initial begin
        $dumpfile("build/shift_register4.vcd");
        $dumpvars(0, tb_shift_register4);

        clk      = 1'b0;
        n_rst    = 1'b1;
        enable   = 1'b0;
        shift_in = 1'b0;
        
        check_reset();

        // RTL assumption:
        // shift_out <= q[0];
        // q         <= {shift_in, q[3:1]};

        check_shift(1'b1, 4'b1000, 1'b0);
        check_shift(1'b0, 4'b0100, 1'b0);
        check_shift(1'b1, 4'b1010, 1'b0);
        check_shift(1'b1, 4'b1101, 1'b0);

        // Hold: q and shift_out should not change when enable=0
        check_hold(1'b0, 4'b1101, 1'b0);

        // Continue shifting to observe bits leaving through shift_out
        check_shift(1'b0, 4'b0110, 1'b1);
        check_shift(1'b0, 4'b0011, 1'b0);
        check_shift(1'b0, 4'b0001, 1'b1);
        check_shift(1'b0, 4'b0000, 1'b1);

        $display("4-bit shift register test passed.");
        $finish;
    end

endmodule

verilog-learning/build/shift_register4.vcd
$date
	Sun May 31 10:39:57 2026
$end
$version
	Icarus Verilog
$end
$timescale
	1ps
$end
$scope module tb_shift_register4 $end
$var wire 1 ! shift_out $end
$var wire 4 " q [3:0] $end
$var reg 1 # clk $end
$var reg 1 $ enable $end
$var reg 1 % n_rst $end
$var reg 1 & shift_in $end
$scope module dut $end
$var wire 1 # clk $end
$var wire 1 $ enable $end
$var wire 1 % n_rst $end
$var wire 1 & shift_in $end
$var reg 4 ' q [3:0] $end
$var reg 1 ! shift_out $end
$upscope $end
$scope task check_hold $end
$upscope $end
$scope task check_reset $end
$upscope $end
$scope task check_shift $end
$upscope $end
$upscope $end
$enddefinitions $end
$comment Show the parameter values. $end
$dumpall
$end
#0
$dumpvars
b0 '
0&
0%
0$
0#
b0 "
0!
$end
#1000
1%
#2000
1&
1$
#5000
b1000 "
b1000 '
1#
#6000
0&
#10000
0#
#15000
b100 "
b100 '
1#
#16000
1&
#20000
0#
#25000
b1010 "
b1010 '
1#
#30000
0#
#35000
b1101 "
b1101 '
1#
#36000
0&
0$
#40000
0#
#45000
1#
#46000
1$
#50000
0#
#55000
b110 "
b110 '
1!
1#
#60000
0#
#65000
b11 "
b11 '
0!
1#
#70000
0#
#75000
b1 "
b1 '
1!
1#
#80000
0#
#85000
b0 "
b0 '
1#
