rtl/common/synchronizer.sv
// 2 flop synchronizer useful for signals wiht differnet clock domains to reduce the chance of metastability
// in case a value changes right before a clock edge transition the 2 flop synchronizer can reduce that risk
// placed on the rx side

module synchronizer (
    input logic clk,
    input logic n_rst,
    input logic in_sig,
    output logic out_sig
);

logic a;
logic b;

always_ff @(posedge clk or negedge n_rst ) begin
    if (!n_rst) begin
        a <= 0;
        b <= 0;
    end else begin    
        a <= in_sig;
        b <= a; 
    end
end

assign out_sig = b;

endmodule

tb/common/tb_synchronizer.sv
`timescale 1ns/1ps

module tb_synchronizer;

    logic clk;
    logic n_rst;
    logic in_sig;
    logic out_sig;
    
    synchronizer dut (
        .clk(clk),
        .n_rst(n_rst),
        .in_sig(in_sig),
        .out_sig(out_sig)
    );

    always #5 clk = ~clk;

    task automatic check_reset(); 
        begin
            n_rst   = 1'b0;
            #1;

            if (out_sig != 1'b0) begin
                $fatal(1, "FAILED reset: expected out_sig=0000 got out_sig=%04b", out_sig); 
            end

            n_rst = 1'b1;
            #1;
        end
    endtask

    task automatic check_input_change(
        input realtime delay,
        input logic new_in_sig,
        input logic old_out_sig
    );
        begin
            n_rst = 1'b1;

            @(posedge clk);
            #delay;
            in_sig = new_in_sig;
            if (out_sig != old_out_sig) begin
                $fatal(1, "out_sig changed immediately: Received: out_sig=%0b Expected: out_sig=%0b", out_sig, old_out_sig);
            end

            @(posedge clk);
            #1;
            if (out_sig != old_out_sig) begin
                $fatal(1, "out_sig changed after one edge only: Received: out_sig=%0b Expected: out_sig=%0b", out_sig, old_out_sig);
            end

            @(posedge clk);
            #1;
            if (out_sig != new_in_sig) begin
                $fatal(1, "out_sig != in_sig: Received: out_sig=%0b Expected: out_sig=%0b", out_sig, new_in_sig);
            end
        end
    endtask

    initial begin
        $dumpfile("build/synchronizer.vcd");
        $dumpvars(0, tb_synchronizer);

        clk      = 1'b0;
        n_rst    = 1'b1;
        in_sig   = 1'b0;
        
        check_reset();

        for (int i = 1; i < 10; i++) begin
            if (i != 5) begin    
                check_input_change(i, 1, 0);
                check_input_change(i, 0, 1); 
            end
        end

        check_input_change(0.01, 1, 0);
        check_input_change(9.99, 0, 1);
        check_input_change(0.01, 1, 0);
        check_input_change(9.99, 0, 1);

        $display("Synchronizer test passed.");
        $finish;
    end

endmodule

build/synchronizer.vcd
$date
	Thu Jun  4 07:13:30 2026
$end
$version
	Icarus Verilog
$end
$timescale
	1ps
$end
$scope module tb_synchronizer $end
$var wire 1 ! out_sig $end
$var reg 1 " clk $end
$var reg 1 # in_sig $end
$var reg 1 $ n_rst $end
$scope module dut $end
$var wire 1 " clk $end
$var wire 1 # in_sig $end
$var wire 1 $ n_rst $end
$var wire 1 ! out_sig $end
$var reg 1 % a $end
$var reg 1 & b $end
$upscope $end
$scope begin $ivl_for_loop0 $end
$var integer 32 ' i [31:0] $end
$upscope $end
$scope task check_input_change $end
$upscope $end
$scope task check_reset $end
$upscope $end
$upscope $end
$enddefinitions $end
$comment Show the parameter values. $end
$dumpall
$end
#0
$dumpvars
b0 '
0&
0%
0$
0#
0"
0!
$end
#1000
1$
#2000
b1 '
#5000
1"
#6000
1#
#10000
0"
#15000
1%
1"
#20000
0"
#25000
1!
1&
1"
#30000
0"
#35000
1"
#36000
0#
#40000
0"
#45000
0%
1"
#50000
0"
#55000
0!
0&
1"
#56000
b10 '
#60000
0"
#65000
1"
#67000
1#
#70000
0"
#75000
1%
1"
#80000
0"
#85000
1!
1&
1"
#90000
0"
#95000
1"
#97000
0#
#100000
0"
#105000
0%
1"
#110000
0"
#115000
0!
0&
1"
#116000
b11 '
#120000
0"
#125000
1"
#128000
1#
#130000
0"
#135000
1%
1"
#140000
0"
#145000
1!
1&
1"
#150000
0"
#155000
1"
#158000
0#
#160000
0"
#165000
0%
1"
#170000
0"
#175000
0!
0&
1"
#176000
b100 '
#180000
0"
#185000
1"
#189000
1#
#190000
0"
#195000
1%
1"
#200000
0"
#205000
1!
1&
1"
#210000
0"
#215000
1"
#219000
0#
#220000
0"
#225000
0%
1"
#230000
0"
#235000
0!
0&
1"
#236000
b110 '
#240000
0"
#245000
1"
#250000
0"
#251000
1#
#255000
1%
1"
#260000
0"
#265000
1!
1&
1"
#270000
0"
#275000
1"
#280000
0"
#281000
0#
#285000
0%
1"
#290000
0"
#295000
0!
0&
1"
#296000
b111 '
#300000
0"
#305000
1"
#310000
0"
#312000
1#
#315000
1%
1"
#320000
0"
#325000
1!
1&
1"
#330000
0"
#335000
1"
#340000
0"
#342000
0#
#345000
0%
1"
#350000
0"
#355000
0!
0&
1"
#356000
b1000 '
#360000
0"
#365000
1"
#370000
0"
#373000
1#
#375000
1%
1"
#380000
0"
#385000
1!
1&
1"
#390000
0"
#395000
1"
#400000
0"
#403000
0#
#405000
0%
1"
#410000
0"
#415000
0!
0&
1"
#416000
b1001 '
#420000
0"
#425000
1"
#430000
0"
#434000
1#
#435000
1%
1"
#440000
0"
#445000
1!
1&
1"
#450000
0"
#455000
1"
#460000
0"
#464000
0#
#465000
0%
1"
#470000
0"
#475000
0!
0&
1"
#476000
b1010 '
#480000
0"
#485000
1"
#485010
1#
#490000
0"
#495000
1%
1"
#500000
0"
#505000
1!
1&
1"
#510000
0"
#515000
1"
#520000
0"
#524990
0#
#525000
0%
1"
#530000
0"
#535000
0!
0&
1"
#540000
0"
#545000
1"
#545010
1#
#550000
0"
#555000
1%
1"
#560000
0"
#565000
1!
1&
1"
#570000
0"
#575000
1"
#580000
0"
#584990
0#
#585000
0%
1"
#590000
0"
#595000
0!
0&
1"
